captain_hooks-0.2.1.dist-info/METADATA
captain_hooks-0.2.1.dist-info/WHEEL
captain_hooks-0.2.1.dist-info/entry_points.txt
captain_hooks/__init__.py
captain_hooks/meson_file_list.py
captain_hooks/compat.py
captain_hooks/vendored/__init__.py
captain_hooks/vendored/_argparse.py
captain_hooks-0.2.1.dist-info/RECORD
