Metadata-Version: 2.1
Name: captain-hooks
Version: 0.2.1
Summary: Collection of pre-commit hooks
Author-Email: Toshio Kuratomi <a.badger@gmail.com>
Classifier: Intended Audience :: Developers
Classifier: License :: OSI Approved :: GNU Affero General Public License v3 or later (AGPLv3+)
Classifier: Programming Language :: Python :: 3
Classifier: Topic :: Software Development :: Libraries :: Python Modules
Project-URL: Repository, https://github.com/abadger/captain-hooks
Project-URL: Documentation, https://readthedocs.io/captain-hooks
Requires-Python: ~=3.0
